skill_user_settings/LICENSE.md
skill_user_settings/README.md
skill_user_settings/__init__.py
skill_user_settings/skill.json
skill_user_settings/version.py
skill_user_settings/locale/en-us/languages.value
skill_user_settings/locale/en-us/dialog/also_change_location_tz.dialog
skill_user_settings/locale/en-us/dialog/birthday_confirmed.dialog
skill_user_settings/locale/en-us/dialog/birthday_is.dialog
skill_user_settings/locale/en-us/dialog/birthday_not_heard.dialog
skill_user_settings/locale/en-us/dialog/birthday_not_known.dialog
skill_user_settings/locale/en-us/dialog/change_location_tz.dialog
skill_user_settings/locale/en-us/dialog/date_format_already_set.dialog
skill_user_settings/locale/en-us/dialog/date_format_changed.dialog
skill_user_settings/locale/en-us/dialog/dialog_mode_already_set.dialog
skill_user_settings/locale/en-us/dialog/dialog_mode_changed.dialog
skill_user_settings/locale/en-us/dialog/email_already_set_same.dialog
skill_user_settings/locale/en-us/dialog/email_confirmation.dialog
skill_user_settings/locale/en-us/dialog/email_is.dialog
skill_user_settings/locale/en-us/dialog/email_not_changed.dialog
skill_user_settings/locale/en-us/dialog/email_not_confirmed.dialog
skill_user_settings/locale/en-us/dialog/email_not_known.dialog
skill_user_settings/locale/en-us/dialog/email_overwrite.dialog
skill_user_settings/locale/en-us/dialog/email_set.dialog
skill_user_settings/locale/en-us/dialog/email_set_error.dialog
skill_user_settings/locale/en-us/dialog/error_change_username.dialog
skill_user_settings/locale/en-us/dialog/happy_birthday.dialog
skill_user_settings/locale/en-us/dialog/hesitation_disabled.dialog
skill_user_settings/locale/en-us/dialog/hesitation_enabled.dialog
skill_user_settings/locale/en-us/dialog/language_change_confirmation.dialog
skill_user_settings/locale/en-us/dialog/language_not_changed.dialog
skill_user_settings/locale/en-us/dialog/language_not_confirmed.dialog
skill_user_settings/locale/en-us/dialog/language_not_heard.dialog
skill_user_settings/neon_skill_user_settings.egg-info/PKG-INFO
skill_user_settings/neon_skill_user_settings.egg-info/SOURCES.txt
skill_user_settings/neon_skill_user_settings.egg-info/dependency_links.txt
skill_user_settings/neon_skill_user_settings.egg-info/entry_points.txt
skill_user_settings/neon_skill_user_settings.egg-info/requires.txt
skill_user_settings/neon_skill_user_settings.egg-info/top_level.txt
neon_skill_user_settings-1.1.0.dist-info/LICENSE.md
neon_skill_user_settings-1.1.0.dist-info/METADATA
neon_skill_user_settings-1.1.0.dist-info/WHEEL
neon_skill_user_settings-1.1.0.dist-info/entry_points.txt
neon_skill_user_settings-1.1.0.dist-info/top_level.txt
neon_skill_user_settings-1.1.0.dist-info/RECORD
